{
    "Pyorbit_Lattice": {
        "file_name": "sns_linac.xml",
        "subsections": [
            "SCLMed",
            "SCLHigh",
            "HEBT1"
        ]
    },
    "Devices": {
        "Cavities": {
            "parameters": {
                "CtlPhaseSet": {
                    "parameter_key": "phase",
                    "pv_type": "setting"
                },
                "CtlAmpSet": {
                    "parameter_key": "amp",
                    "pv_type": "setting"
                },
                "BlnkBeam": {
                    "parameter_key": "blanked",
                    "pv_type": "setting"
                }
            },
            "devices": {
                "SCL_LLRF:FCM01a": {
                    "pyorbit_name": "SCL:Cav01a",
                    "override": {
                        "CtlAmpSet": {
                            "linear_offset": 14.9339
                        },
                        "CtlPhaseSet": {
                            "phase_offset": -17.77005077038193
                        }
                    }
                },
                "SCL_LLRF:FCM01b": {
                    "pyorbit_name": "SCL:Cav01b",
                    "override": {
                        "CtlAmpSet": {
                            "linear_offset": 14.9339
                        },
                        "CtlPhaseSet": {
                            "phase_offset": 9.799191229499161
                        }
                    }
                },
                "SCL_LLRF:FCM01c": {
                    "pyorbit_name": "SCL:Cav01c",
                    "override": {
                        "CtlAmpSet": {
                            "linear_offset": 14.9339
                        },
                        "CtlPhaseSet": {
                            "phase_offset": 69.89786518721455
                        }
                    }
                },
                "SCL_LLRF:FCM02a": {
                    "pyorbit_name": "SCL:Cav02a",
                    "override": {
                        "CtlAmpSet": {
                            "linear_offset": 14.9339
                        },
                        "CtlPhaseSet": {
                            "phase_offset": 27.13563604464474
                        }
                    }
                },
                "SCL_LLRF:FCM02b": {
                    "pyorbit_name": "SCL:Cav02b",
                    "override": {
                        "CtlAmpSet": {
                            "linear_offset": 14.9339
                        },
                        "CtlPhaseSet": {
                            "phase_offset": -177.1526079917464
                        }
                    }
                },
                "SCL_LLRF:FCM02c": {
                    "pyorbit_name": "SCL:Cav02c",
                    "override": {
                        "CtlAmpSet": {
                            "linear_offset": 14.9339
                        },
                        "CtlPhaseSet": {
                            "phase_offset": -141.36513182397792
                        }
                    }
                },
                "SCL_LLRF:FCM03a": {
                    "pyorbit_name": "SCL:Cav03a",
                    "override": {
                        "CtlAmpSet": {
                            "linear_offset": 14.9339
                        },
                        "CtlPhaseSet": {
                            "phase_offset": 74.98584814159946
                        }
                    }
                },
                "SCL_LLRF:FCM03b": {
                    "pyorbit_name": "SCL:Cav03b",
                    "override": {
                        "CtlAmpSet": {
                            "linear_offset": 14.9339
                        },
                        "CtlPhaseSet": {
                            "phase_offset": 32.964467808696426
                        }
                    }
                },
                "SCL_LLRF:FCM03c": {
                    "pyorbit_name": "SCL:Cav03c",
                    "override": {
                        "CtlAmpSet": {
                            "linear_offset": 14.9339
                        },
                        "CtlPhaseSet": {
                            "phase_offset": 46.585888245097465
                        }
                    }
                },
                "SCL_LLRF:FCM04a": {
                    "pyorbit_name": "SCL:Cav04a",
                    "override": {
                        "CtlAmpSet": {
                            "linear_offset": 14.9339
                        },
                        "CtlPhaseSet": {
                            "phase_offset": 73.20908543244607
                        }
                    }
                },
                "SCL_LLRF:FCM04b": {
                    "pyorbit_name": "SCL:Cav04b",
                    "override": {
                        "CtlAmpSet": {
                            "linear_offset": 14.9339
                        },
                        "CtlPhaseSet": {
                            "phase_offset": 91.58054313806224
                        }
                    }
                },
                "SCL_LLRF:FCM04c": {
                    "pyorbit_name": "SCL:Cav04c",
                    "override": {
                        "CtlAmpSet": {
                            "linear_offset": 14.9339
                        },
                        "CtlPhaseSet": {
                            "phase_offset": 93.04927295448353
                        }
                    }
                },
                "SCL_LLRF:FCM05a": {
                    "pyorbit_name": "SCL:Cav05a",
                    "override": {
                        "CtlAmpSet": {
                            "linear_offset": 14.9339
                        },
                        "CtlPhaseSet": {
                            "phase_offset": -15.72213649062764
                        }
                    }
                },
                "SCL_LLRF:FCM05b": {
                    "pyorbit_name": "SCL:Cav05b",
                    "override": {
                        "CtlAmpSet": {
                            "linear_offset": 14.9339
                        },
                        "CtlPhaseSet": {
                            "phase_offset": -173.5905848486042
                        }
                    }
                },
                "SCL_LLRF:FCM05c": {
                    "pyorbit_name": "SCL:Cav05c",
                    "override": {
                        "CtlAmpSet": {
                            "linear_offset": 14.9339
                        },
                        "CtlPhaseSet": {
                            "phase_offset": -27.578672546785118
                        }
                    }
                },
                "SCL_LLRF:FCM06a": {
                    "pyorbit_name": "SCL:Cav06a",
                    "override": {
                        "CtlAmpSet": {
                            "linear_offset": 14.9339
                        },
                        "CtlPhaseSet": {
                            "phase_offset": -20.195271756883685
                        }
                    }
                },
                "SCL_LLRF:FCM06b": {
                    "pyorbit_name": "SCL:Cav06b",
                    "override": {
                        "CtlAmpSet": {
                            "linear_offset": 14.9339
                        },
                        "CtlPhaseSet": {
                            "phase_offset": -66.31726689805582
                        }
                    }
                },
                "SCL_LLRF:FCM06c": {
                    "pyorbit_name": "SCL:Cav06c",
                    "override": {
                        "CtlAmpSet": {
                            "linear_offset": 14.9339
                        },
                        "CtlPhaseSet": {
                            "phase_offset": -4.850309148541125
                        }
                    }
                },
                "SCL_LLRF:FCM07a": {
                    "pyorbit_name": "SCL:Cav07a",
                    "override": {
                        "CtlAmpSet": {
                            "linear_offset": 14.9339
                        },
                        "CtlPhaseSet": {
                            "phase_offset": -159.46353041611167
                        }
                    }
                },
                "SCL_LLRF:FCM07b": {
                    "pyorbit_name": "SCL:Cav07b",
                    "override": {
                        "CtlAmpSet": {
                            "linear_offset": 14.9339
                        },
                        "CtlPhaseSet": {
                            "phase_offset": -153.73602894246378
                        }
                    }
                },
                "SCL_LLRF:FCM07c": {
                    "pyorbit_name": "SCL:Cav07c",
                    "override": {
                        "CtlAmpSet": {
                            "linear_offset": 14.9339
                        },
                        "CtlPhaseSet": {
                            "phase_offset": -101.47138751819786
                        }
                    }
                },
                "SCL_LLRF:FCM08a": {
                    "pyorbit_name": "SCL:Cav08a",
                    "override": {
                        "CtlAmpSet": {
                            "linear_offset": 14.9339
                        },
                        "CtlPhaseSet": {
                            "phase_offset": 97.84615323427528
                        }
                    }
                },
                "SCL_LLRF:FCM08b": {
                    "pyorbit_name": "SCL:Cav08b",
                    "override": {
                        "CtlAmpSet": {
                            "linear_offset": 14.9339
                        },
                        "CtlPhaseSet": {
                            "phase_offset": -173.50150709438324
                        }
                    }
                },
                "SCL_LLRF:FCM08c": {
                    "pyorbit_name": "SCL:Cav08c",
                    "override": {
                        "CtlAmpSet": {
                            "linear_offset": 14.9339
                        },
                        "CtlPhaseSet": {
                            "phase_offset": 139.70624872419756
                        }
                    }
                },
                "SCL_LLRF:FCM09a": {
                    "pyorbit_name": "SCL:Cav09a",
                    "override": {
                        "CtlAmpSet": {
                            "linear_offset": 14.9339
                        },
                        "CtlPhaseSet": {
                            "phase_offset": -83.75181276447127
                        }
                    }
                },
                "SCL_LLRF:FCM09b": {
                    "pyorbit_name": "SCL:Cav09b",
                    "override": {
                        "CtlAmpSet": {
                            "linear_offset": 14.9339
                        },
                        "CtlPhaseSet": {
                            "phase_offset": 113.33365565406454
                        }
                    }
                },
                "SCL_LLRF:FCM09c": {
                    "pyorbit_name": "SCL:Cav09c",
                    "override": {
                        "CtlAmpSet": {
                            "linear_offset": 14.9339
                        },
                        "CtlPhaseSet": {
                            "phase_offset": -117.79535795473596
                        }
                    }
                },
                "SCL_LLRF:FCM10a": {
                    "pyorbit_name": "SCL:Cav10a",
                    "override": {
                        "CtlAmpSet": {
                            "linear_offset": 14.9339
                        },
                        "CtlPhaseSet": {
                            "phase_offset": -78.44292618911463
                        }
                    }
                },
                "SCL_LLRF:FCM10b": {
                    "pyorbit_name": "SCL:Cav10b",
                    "override": {
                        "CtlAmpSet": {
                            "linear_offset": 14.9339
                        },
                        "CtlPhaseSet": {
                            "phase_offset": 169.55248042425484
                        }
                    }
                },
                "SCL_LLRF:FCM10c": {
                    "pyorbit_name": "SCL:Cav10c",
                    "override": {
                        "CtlAmpSet": {
                            "linear_offset": 14.9339
                        },
                        "CtlPhaseSet": {
                            "phase_offset": -92.51654338380905
                        }
                    }
                },
                "SCL_LLRF:FCM11a": {
                    "pyorbit_name": "SCL:Cav11a",
                    "override": {
                        "CtlAmpSet": {
                            "linear_offset": 14.9339
                        },
                        "CtlPhaseSet": {
                            "phase_offset": -179.36413670687017
                        }
                    }
                },
                "SCL_LLRF:FCM11b": {
                    "pyorbit_name": "SCL:Cav11b",
                    "override": {
                        "CtlAmpSet": {
                            "linear_offset": 14.9339
                        },
                        "CtlPhaseSet": {
                            "phase_offset": 34.102215590006274
                        }
                    }
                },
                "SCL_LLRF:FCM11c": {
                    "pyorbit_name": "SCL:Cav11c",
                    "override": {
                        "CtlAmpSet": {
                            "linear_offset": 14.9339
                        },
                        "CtlPhaseSet": {
                            "phase_offset": 97.0992403139871
                        }
                    }
                },
                "SCL_LLRF:FCM12a": {
                    "pyorbit_name": "SCL:Cav12a",
                    "override": {
                        "CtlAmpSet": {
                            "linear_offset": 14.9339
                        },
                        "CtlPhaseSet": {
                            "phase_offset": -90.38023794210295
                        }
                    }
                },
                "SCL_LLRF:FCM12b": {
                    "pyorbit_name": "SCL:Cav12b",
                    "override": {
                        "CtlAmpSet": {
                            "linear_offset": 14.9339
                        },
                        "CtlPhaseSet": {
                            "phase_offset": 131.5389400032716
                        }
                    }
                },
                "SCL_LLRF:FCM12c": {
                    "pyorbit_name": "SCL:Cav12c",
                    "override": {
                        "CtlAmpSet": {
                            "linear_offset": 14.9339
                        },
                        "CtlPhaseSet": {
                            "phase_offset": 77.32278570967456
                        }
                    }
                },
                "SCL_LLRF:FCM12d": {
                    "pyorbit_name": "SCL:Cav12d",
                    "override": {
                        "CtlAmpSet": {
                            "linear_offset": 14.9339
                        },
                        "CtlPhaseSet": {
                            "phase_offset": 8.774897568490218
                        }
                    }
                },
                "SCL_LLRF:FCM13a": {
                    "pyorbit_name": "SCL:Cav13a",
                    "override": {
                        "CtlAmpSet": {
                            "linear_offset": 14.9339
                        },
                        "CtlPhaseSet": {
                            "phase_offset": -77.77856772299764
                        }
                    }
                },
                "SCL_LLRF:FCM13b": {
                    "pyorbit_name": "SCL:Cav13b",
                    "override": {
                        "CtlAmpSet": {
                            "linear_offset": 14.9339
                        },
                        "CtlPhaseSet": {
                            "phase_offset": -111.98582646607164
                        }
                    }
                },
                "SCL_LLRF:FCM13c": {
                    "pyorbit_name": "SCL:Cav13c",
                    "override": {
                        "CtlAmpSet": {
                            "linear_offset": 14.9339
                        },
                        "CtlPhaseSet": {
                            "phase_offset": -108.97951371306516
                        }
                    }
                },
                "SCL_LLRF:FCM13d": {
                    "pyorbit_name": "SCL:Cav13d",
                    "override": {
                        "CtlAmpSet": {
                            "linear_offset": 14.9339
                        },
                        "CtlPhaseSet": {
                            "phase_offset": 19.61607351242348
                        }
                    }
                },
                "SCL_LLRF:FCM14a": {
                    "pyorbit_name": "SCL:Cav14a",
                    "override": {
                        "CtlAmpSet": {
                            "linear_offset": 14.9339
                        },
                        "CtlPhaseSet": {
                            "phase_offset": 114.87253761069124
                        }
                    }
                },
                "SCL_LLRF:FCM14b": {
                    "pyorbit_name": "SCL:Cav14b",
                    "override": {
                        "CtlAmpSet": {
                            "linear_offset": 14.9339
                        },
                        "CtlPhaseSet": {
                            "phase_offset": -5.071680601746769
                        }
                    }
                },
                "SCL_LLRF:FCM14c": {
                    "pyorbit_name": "SCL:Cav14c",
                    "override": {
                        "CtlAmpSet": {
                            "linear_offset": 14.9339
                        },
                        "CtlPhaseSet": {
                            "phase_offset": -43.38886210032356
                        }
                    }
                },
                "SCL_LLRF:FCM14d": {
                    "pyorbit_name": "SCL:Cav14d",
                    "override": {
                        "CtlAmpSet": {
                            "linear_offset": 14.9339
                        },
                        "CtlPhaseSet": {
                            "phase_offset": -95.70152816711658
                        }
                    }
                },
                "SCL_LLRF:FCM15a": {
                    "pyorbit_name": "SCL:Cav15a",
                    "override": {
                        "CtlAmpSet": {
                            "linear_offset": 14.9339
                        },
                        "CtlPhaseSet": {
                            "phase_offset": -30.245263159416837
                        }
                    }
                },
                "SCL_LLRF:FCM15b": {
                    "pyorbit_name": "SCL:Cav15b",
                    "override": {
                        "CtlAmpSet": {
                            "linear_offset": 14.9339
                        },
                        "CtlPhaseSet": {
                            "phase_offset": -81.27735841071191
                        }
                    }
                },
                "SCL_LLRF:FCM15c": {
                    "pyorbit_name": "SCL:Cav15c",
                    "override": {
                        "CtlAmpSet": {
                            "linear_offset": 14.9339
                        },
                        "CtlPhaseSet": {
                            "phase_offset": -97.75050542062385
                        }
                    }
                },
                "SCL_LLRF:FCM15d": {
                    "pyorbit_name": "SCL:Cav15d",
                    "override": {
                        "CtlAmpSet": {
                            "linear_offset": 14.9339
                        },
                        "CtlPhaseSet": {
                            "phase_offset": -107.40394275659374
                        }
                    }
                },
                "SCL_LLRF:FCM16a": {
                    "pyorbit_name": "SCL:Cav16a",
                    "override": {
                        "CtlAmpSet": {
                            "linear_offset": 14.9339
                        },
                        "CtlPhaseSet": {
                            "phase_offset": 110.9766610522539
                        }
                    }
                },
                "SCL_LLRF:FCM16b": {
                    "pyorbit_name": "SCL:Cav16b",
                    "override": {
                        "CtlAmpSet": {
                            "linear_offset": 14.9339
                        },
                        "CtlPhaseSet": {
                            "phase_offset": -50.551993563050026
                        }
                    }
                },
                "SCL_LLRF:FCM16c": {
                    "pyorbit_name": "SCL:Cav16c",
                    "override": {
                        "CtlAmpSet": {
                            "linear_offset": 14.9339
                        },
                        "CtlPhaseSet": {
                            "phase_offset": 117.63064140364675
                        }
                    }
                },
                "SCL_LLRF:FCM16d": {
                    "pyorbit_name": "SCL:Cav16d",
                    "override": {
                        "CtlAmpSet": {
                            "linear_offset": 14.9339
                        },
                        "CtlPhaseSet": {
                            "phase_offset": 72.47687500048421
                        }
                    }
                },
                "SCL_LLRF:FCM17a": {
                    "pyorbit_name": "SCL:Cav17a",
                    "override": {
                        "CtlAmpSet": {
                            "linear_offset": 14.9339
                        },
                        "CtlPhaseSet": {
                            "phase_offset": -61.755608055654
                        }
                    }
                },
                "SCL_LLRF:FCM17b": {
                    "pyorbit_name": "SCL:Cav17b",
                    "override": {
                        "CtlAmpSet": {
                            "linear_offset": 14.9339
                        },
                        "CtlPhaseSet": {
                            "phase_offset": 104.1361613165596
                        }
                    }
                },
                "SCL_LLRF:FCM17c": {
                    "pyorbit_name": "SCL:Cav17c",
                    "override": {
                        "CtlAmpSet": {
                            "linear_offset": 14.9339
                        },
                        "CtlPhaseSet": {
                            "phase_offset": -70.12753997634182
                        }
                    }
                },
                "SCL_LLRF:FCM17d": {
                    "pyorbit_name": "SCL:Cav17d",
                    "override": {
                        "CtlAmpSet": {
                            "linear_offset": 14.9339
                        },
                        "CtlPhaseSet": {
                            "phase_offset": 7.8753076930131405
                        }
                    }
                },
                "SCL_LLRF:FCM18a": {
                    "pyorbit_name": "SCL:Cav18a",
                    "override": {
                        "CtlAmpSet": {
                            "linear_offset": 14.9339
                        },
                        "CtlPhaseSet": {
                            "phase_offset": 65.05396625256776
                        }
                    }
                },
                "SCL_LLRF:FCM18b": {
                    "pyorbit_name": "SCL:Cav18b",
                    "override": {
                        "CtlAmpSet": {
                            "linear_offset": 14.9339
                        },
                        "CtlPhaseSet": {
                            "phase_offset": -31.59122432259958
                        }
                    }
                },
                "SCL_LLRF:FCM18c": {
                    "pyorbit_name": "SCL:Cav18c",
                    "override": {
                        "CtlAmpSet": {
                            "linear_offset": 14.9339
                        },
                        "CtlPhaseSet": {
                            "phase_offset": 76.85945857922799
                        }
                    }
                },
                "SCL_LLRF:FCM18d": {
                    "pyorbit_name": "SCL:Cav18d",
                    "override": {
                        "CtlAmpSet": {
                            "linear_offset": 14.9339
                        },
                        "CtlPhaseSet": {
                            "phase_offset": -20.532230464859893
                        }
                    }
                },
                "SCL_LLRF:FCM19a": {
                    "pyorbit_name": "SCL:Cav19a",
                    "override": {
                        "CtlAmpSet": {
                            "linear_offset": 14.9339
                        },
                        "CtlPhaseSet": {
                            "phase_offset": 167.49926798822628
                        }
                    }
                },
                "SCL_LLRF:FCM19b": {
                    "pyorbit_name": "SCL:Cav19b",
                    "override": {
                        "CtlAmpSet": {
                            "linear_offset": 14.9339
                        },
                        "CtlPhaseSet": {
                            "phase_offset": 111.25232157091088
                        }
                    }
                },
                "SCL_LLRF:FCM19c": {
                    "pyorbit_name": "SCL:Cav19c",
                    "override": {
                        "CtlAmpSet": {
                            "linear_offset": 14.9339
                        },
                        "CtlPhaseSet": {
                            "phase_offset": -174.93723622996842
                        }
                    }
                },
                "SCL_LLRF:FCM19d": {
                    "pyorbit_name": "SCL:Cav19d",
                    "override": {
                        "CtlAmpSet": {
                            "linear_offset": 14.9339
                        },
                        "CtlPhaseSet": {
                            "phase_offset": -100.64882296959297
                        }
                    }
                },
                "SCL_LLRF:FCM20a": {
                    "pyorbit_name": "SCL:Cav20a",
                    "override": {
                        "CtlAmpSet": {
                            "linear_offset": 14.9339
                        },
                        "CtlPhaseSet": {
                            "phase_offset": -106.19007677715538
                        }
                    }
                },
                "SCL_LLRF:FCM20b": {
                    "pyorbit_name": "SCL:Cav20b",
                    "override": {
                        "CtlAmpSet": {
                            "linear_offset": 14.9339
                        },
                        "CtlPhaseSet": {
                            "phase_offset": 110.3858826505262
                        }
                    }
                },
                "SCL_LLRF:FCM20c": {
                    "pyorbit_name": "SCL:Cav20c",
                    "override": {
                        "CtlAmpSet": {
                            "linear_offset": 14.9339
                        },
                        "CtlPhaseSet": {
                            "phase_offset": -156.47327582623788
                        }
                    }
                },
                "SCL_LLRF:FCM20d": {
                    "pyorbit_name": "SCL:Cav20d",
                    "override": {
                        "CtlAmpSet": {
                            "linear_offset": 14.9339
                        },
                        "CtlPhaseSet": {
                            "phase_offset": -83.24449743020553
                        }
                    }
                },
                "SCL_LLRF:FCM21a": {
                    "pyorbit_name": "SCL:Cav21a",
                    "override": {
                        "CtlAmpSet": {
                            "linear_offset": 14.9339
                        },
                        "CtlPhaseSet": {
                            "phase_offset": 108.3752967556245
                        }
                    }
                },
                "SCL_LLRF:FCM21b": {
                    "pyorbit_name": "SCL:Cav21b",
                    "override": {
                        "CtlAmpSet": {
                            "linear_offset": 14.9339
                        },
                        "CtlPhaseSet": {
                            "phase_offset": 28.400723872310056
                        }
                    }
                },
                "SCL_LLRF:FCM21c": {
                    "pyorbit_name": "SCL:Cav21c",
                    "override": {
                        "CtlAmpSet": {
                            "linear_offset": 14.9339
                        },
                        "CtlPhaseSet": {
                            "phase_offset": 22.545371042355896
                        }
                    }
                },
                "SCL_LLRF:FCM21d": {
                    "pyorbit_name": "SCL:Cav21d",
                    "override": {
                        "CtlAmpSet": {
                            "linear_offset": 14.9339
                        },
                        "CtlPhaseSet": {
                            "phase_offset": 90.73395347896358
                        }
                    }
                },
                "SCL_LLRF:FCM22a": {
                    "pyorbit_name": "SCL:Cav22a",
                    "override": {
                        "CtlAmpSet": {
                            "linear_offset": 14.9339
                        },
                        "CtlPhaseSet": {
                            "phase_offset": -153.03023897766911
                        }
                    }
                },
                "SCL_LLRF:FCM22b": {
                    "pyorbit_name": "SCL:Cav22b",
                    "override": {
                        "CtlAmpSet": {
                            "linear_offset": 14.9339
                        },
                        "CtlPhaseSet": {
                            "phase_offset": 45.27356427532258
                        }
                    }
                },
                "SCL_LLRF:FCM22c": {
                    "pyorbit_name": "SCL:Cav22c",
                    "override": {
                        "CtlAmpSet": {
                            "linear_offset": 14.9339
                        },
                        "CtlPhaseSet": {
                            "phase_offset": -59.858063245256005
                        }
                    }
                },
                "SCL_LLRF:FCM22d": {
                    "pyorbit_name": "SCL:Cav22d",
                    "override": {
                        "CtlAmpSet": {
                            "linear_offset": 14.9339
                        },
                        "CtlPhaseSet": {
                            "phase_offset": 23.11938193841535
                        }
                    }
                },
                "SCL_LLRF:FCM23a": {
                    "pyorbit_name": "SCL:Cav23a",
                    "override": {
                        "CtlAmpSet": {
                            "linear_offset": 14.9339
                        },
                        "CtlPhaseSet": {
                            "phase_offset": 46.93277745104777
                        }
                    }
                },
                "SCL_LLRF:FCM23b": {
                    "pyorbit_name": "SCL:Cav23b",
                    "override": {
                        "CtlAmpSet": {
                            "linear_offset": 14.9339
                        },
                        "CtlPhaseSet": {
                            "phase_offset": 133.20527751645685
                        }
                    }
                },
                "SCL_LLRF:FCM23c": {
                    "pyorbit_name": "SCL:Cav23c",
                    "override": {
                        "CtlAmpSet": {
                            "linear_offset": 14.9339
                        },
                        "CtlPhaseSet": {
                            "phase_offset": 132.9323479350409
                        }
                    }
                },
                "SCL_LLRF:FCM23d": {
                    "pyorbit_name": "SCL:Cav23d",
                    "override": {
                        "CtlAmpSet": {
                            "linear_offset": 14.9339
                        },
                        "CtlPhaseSet": {
                            "phase_offset": 80.35959709992837
                        }
                    }
                }
            }
        },
        "Quadrupoles": {
            "parameters": {
                "B_set": {
                    "parameter_key": "dB/dr",
                    "pv_type": "setting"
                },
                "B": {
                    "parameter_key": "dB/dr",
                    "pv_type": "readback",
                    "noise": 0.0001
                }
            },
            "devices": {
                "SCL_Mag:QH00": {
                    "pyorbit_name": "SCL_Mag:QH00"
                },
                "SCL_Mag:QV00": {
                    "pyorbit_name": "SCL_Mag:QV00"
                },
                "SCL_Mag:QH01": {
                    "pyorbit_name": "SCL_Mag:QH01"
                },
                "SCL_Mag:QV01": {
                    "pyorbit_name": "SCL_Mag:QV01"
                },
                "SCL_Mag:QH02": {
                    "pyorbit_name": "SCL_Mag:QH02"
                },
                "SCL_Mag:QV02": {
                    "pyorbit_name": "SCL_Mag:QV02"
                },
                "SCL_Mag:QH03": {
                    "pyorbit_name": "SCL_Mag:QH03"
                },
                "SCL_Mag:QV03": {
                    "pyorbit_name": "SCL_Mag:QV03"
                },
                "SCL_Mag:QH04": {
                    "pyorbit_name": "SCL_Mag:QH04"
                },
                "SCL_Mag:QV04": {
                    "pyorbit_name": "SCL_Mag:QV04"
                },
                "SCL_Mag:QH05": {
                    "pyorbit_name": "SCL_Mag:QH05"
                },
                "SCL_Mag:QV05": {
                    "pyorbit_name": "SCL_Mag:QV05"
                },
                "SCL_Mag:QH06": {
                    "pyorbit_name": "SCL_Mag:QH06"
                },
                "SCL_Mag:QV06": {
                    "pyorbit_name": "SCL_Mag:QV06"
                },
                "SCL_Mag:QH07": {
                    "pyorbit_name": "SCL_Mag:QH07"
                },
                "SCL_Mag:QV07": {
                    "pyorbit_name": "SCL_Mag:QV07"
                },
                "SCL_Mag:QH08": {
                    "pyorbit_name": "SCL_Mag:QH08"
                },
                "SCL_Mag:QV08": {
                    "pyorbit_name": "SCL_Mag:QV08"
                },
                "SCL_Mag:QH09": {
                    "pyorbit_name": "SCL_Mag:QH09"
                },
                "SCL_Mag:QV09": {
                    "pyorbit_name": "SCL_Mag:QV09"
                },
                "SCL_Mag:QH10": {
                    "pyorbit_name": "SCL_Mag:QH10"
                },
                "SCL_Mag:QV10": {
                    "pyorbit_name": "SCL_Mag:QV10"
                },
                "SCL_Mag:QH11": {
                    "pyorbit_name": "SCL_Mag:QH11"
                },
                "SCL_Mag:QV11": {
                    "pyorbit_name": "SCL_Mag:QV11"
                },
                "SCL_Mag:QH12": {
                    "pyorbit_name": "SCL_Mag:QH12"
                },
                "SCL_Mag:QV12": {
                    "pyorbit_name": "SCL_Mag:QV12"
                },
                "SCL_Mag:QH13": {
                    "pyorbit_name": "SCL_Mag:QH13"
                },
                "SCL_Mag:QV13": {
                    "pyorbit_name": "SCL_Mag:QV13"
                },
                "SCL_Mag:QH14": {
                    "pyorbit_name": "SCL_Mag:QH14"
                },
                "SCL_Mag:QV14": {
                    "pyorbit_name": "SCL_Mag:QV14"
                },
                "SCL_Mag:QH15": {
                    "pyorbit_name": "SCL_Mag:QH15"
                },
                "SCL_Mag:QV15": {
                    "pyorbit_name": "SCL_Mag:QV15"
                },
                "SCL_Mag:QH16": {
                    "pyorbit_name": "SCL_Mag:QH16"
                },
                "SCL_Mag:QV16": {
                    "pyorbit_name": "SCL_Mag:QV16"
                },
                "SCL_Mag:QH17": {
                    "pyorbit_name": "SCL_Mag:QH17"
                },
                "SCL_Mag:QV17": {
                    "pyorbit_name": "SCL_Mag:QV17"
                },
                "SCL_Mag:QH18": {
                    "pyorbit_name": "SCL_Mag:QH18"
                },
                "SCL_Mag:QV18": {
                    "pyorbit_name": "SCL_Mag:QV18"
                },
                "SCL_Mag:QH19": {
                    "pyorbit_name": "SCL_Mag:QH19"
                },
                "SCL_Mag:QV19": {
                    "pyorbit_name": "SCL_Mag:QV19"
                },
                "SCL_Mag:QH20": {
                    "pyorbit_name": "SCL_Mag:QH20"
                },
                "SCL_Mag:QV20": {
                    "pyorbit_name": "SCL_Mag:QV20"
                },
                "SCL_Mag:QH21": {
                    "pyorbit_name": "SCL_Mag:QH21"
                },
                "SCL_Mag:QV21": {
                    "pyorbit_name": "SCL_Mag:QV21"
                },
                "SCL_Mag:QH22": {
                    "pyorbit_name": "SCL_Mag:QH22"
                },
                "SCL_Mag:QV22": {
                    "pyorbit_name": "SCL_Mag:QV22"
                },
                "SCL_Mag:QH23": {
                    "pyorbit_name": "SCL_Mag:QH23"
                },
                "SCL_Mag:QV23": {
                    "pyorbit_name": "SCL_Mag:QV23"
                },
                "SCL_Mag:QH24": {
                    "pyorbit_name": "SCL_Mag:QH24"
                },
                "SCL_Mag:QV24": {
                    "pyorbit_name": "SCL_Mag:QV24"
                },
                "SCL_Mag:QH25": {
                    "pyorbit_name": "SCL_Mag:QH25"
                },
                "SCL_Mag:QV25": {
                    "pyorbit_name": "SCL_Mag:QV25"
                },
                "SCL_Mag:QH26": {
                    "pyorbit_name": "SCL_Mag:QH26"
                },
                "SCL_Mag:QV26": {
                    "pyorbit_name": "SCL_Mag:QV26"
                },
                "SCL_Mag:QH27": {
                    "pyorbit_name": "SCL_Mag:QH27"
                },
                "SCL_Mag:QV27": {
                    "pyorbit_name": "SCL_Mag:QV27"
                },
                "SCL_Mag:QH28": {
                    "pyorbit_name": "SCL_Mag:QH28"
                },
                "SCL_Mag:QV28": {
                    "pyorbit_name": "SCL_Mag:QV28"
                },
                "SCL_Mag:QH29": {
                    "pyorbit_name": "SCL_Mag:QH29"
                },
                "SCL_Mag:QV29": {
                    "pyorbit_name": "SCL_Mag:QV29"
                },
                "SCL_Mag:QH30": {
                    "pyorbit_name": "SCL_Mag:QH30"
                },
                "SCL_Mag:QV30": {
                    "pyorbit_name": "SCL_Mag:QV30"
                },
                "SCL_Mag:QH31": {
                    "pyorbit_name": "SCL_Mag:QH31"
                },
                "SCL_Mag:QV31": {
                    "pyorbit_name": "SCL_Mag:QV31"
                },
                "SCL_Mag:QH32": {
                    "pyorbit_name": "SCL_Mag:QH32"
                },
                "SCL_Mag:QV32": {
                    "pyorbit_name": "SCL_Mag:QV32"
                },
                "SCL_Mag:QH33": {
                    "pyorbit_name": "SCL_Mag:QH33"
                },
                "HEBT_Mag:QV01": {
                    "pyorbit_name": "HEBT_Mag:QV01"
                },
                "HEBT_Mag:QH02": {
                    "pyorbit_name": "HEBT_Mag:QH02"
                },
                "HEBT_Mag:QV03": {
                    "pyorbit_name": "HEBT_Mag:QV03"
                },
                "HEBT_Mag:QH04": {
                    "pyorbit_name": "HEBT_Mag:QH04"
                },
                "HEBT_Mag:QV05": {
                    "pyorbit_name": "HEBT_Mag:QV05"
                },
                "HEBT_Mag:QH06": {
                    "pyorbit_name": "HEBT_Mag:QH06"
                },
                "HEBT_Mag:QV07": {
                    "pyorbit_name": "HEBT_Mag:QV07"
                },
                "HEBT_Mag:QH08": {
                    "pyorbit_name": "HEBT_Mag:QH08"
                },
                "HEBT_Mag:QV09": {
                    "pyorbit_name": "HEBT_Mag:QV09"
                },
                "HEBT_Mag:QH10": {
                    "pyorbit_name": "HEBT_Mag:QH10"
                },
                "HEBT_Mag:QV11": {
                    "pyorbit_name": "HEBT_Mag:QV11"
                }
            }
        },
        "Correctors": {
            "parameters": {
                "B_set": {
                    "parameter_key": "B",
                    "pv_type": "setting"
                },
                "B": {
                    "parameter_key": "B",
                    "pv_type": "readback",
                    "noise": 0.0001
                }
            },
            "devices": {
                "SCL_Mag:DCH00": {
                    "pyorbit_name": "SCL_Mag:DCH00"
                },
                "SCL_Mag:DCV00": {
                    "pyorbit_name": "SCL_Mag:DCV00"
                },
                "SCL_Mag:DCH01": {
                    "pyorbit_name": "SCL_Mag:DCH01"
                },
                "SCL_Mag:DCV01": {
                    "pyorbit_name": "SCL_Mag:DCV01"
                },
                "SCL_Mag:DCH02": {
                    "pyorbit_name": "SCL_Mag:DCH02"
                },
                "SCL_Mag:DCV02": {
                    "pyorbit_name": "SCL_Mag:DCV02"
                },
                "SCL_Mag:DCH03": {
                    "pyorbit_name": "SCL_Mag:DCH03"
                },
                "SCL_Mag:DCV03": {
                    "pyorbit_name": "SCL_Mag:DCV03"
                },
                "SCL_Mag:DCH04": {
                    "pyorbit_name": "SCL_Mag:DCH04"
                },
                "SCL_Mag:DCV04": {
                    "pyorbit_name": "SCL_Mag:DCV04"
                },
                "SCL_Mag:DCH05": {
                    "pyorbit_name": "SCL_Mag:DCH05"
                },
                "SCL_Mag:DCV05": {
                    "pyorbit_name": "SCL_Mag:DCV05"
                },
                "SCL_Mag:DCH06": {
                    "pyorbit_name": "SCL_Mag:DCH06"
                },
                "SCL_Mag:DCV06": {
                    "pyorbit_name": "SCL_Mag:DCV06"
                },
                "SCL_Mag:DCH07": {
                    "pyorbit_name": "SCL_Mag:DCH07"
                },
                "SCL_Mag:DCV07": {
                    "pyorbit_name": "SCL_Mag:DCV07"
                },
                "SCL_Mag:DCH08": {
                    "pyorbit_name": "SCL_Mag:DCH08"
                },
                "SCL_Mag:DCV08": {
                    "pyorbit_name": "SCL_Mag:DCV08"
                },
                "SCL_Mag:DCH09": {
                    "pyorbit_name": "SCL_Mag:DCH09"
                },
                "SCL_Mag:DCV09": {
                    "pyorbit_name": "SCL_Mag:DCV09"
                },
                "SCL_Mag:DCH10": {
                    "pyorbit_name": "SCL_Mag:DCH10"
                },
                "SCL_Mag:DCV10": {
                    "pyorbit_name": "SCL_Mag:DCV10"
                },
                "SCL_Mag:DCH11": {
                    "pyorbit_name": "SCL_Mag:DCH11"
                },
                "SCL_Mag:DCV11": {
                    "pyorbit_name": "SCL_Mag:DCV11"
                },
                "SCL_Mag:DCH12": {
                    "pyorbit_name": "SCL_Mag:DCH12"
                },
                "SCL_Mag:DCV12": {
                    "pyorbit_name": "SCL_Mag:DCV12"
                },
                "SCL_Mag:DCH13": {
                    "pyorbit_name": "SCL_Mag:DCH13"
                },
                "SCL_Mag:DCV13": {
                    "pyorbit_name": "SCL_Mag:DCV13"
                },
                "SCL_Mag:DCH14": {
                    "pyorbit_name": "SCL_Mag:DCH14"
                },
                "SCL_Mag:DCV14": {
                    "pyorbit_name": "SCL_Mag:DCV14"
                },
                "SCL_Mag:DCH15": {
                    "pyorbit_name": "SCL_Mag:DCH15"
                },
                "SCL_Mag:DCV15": {
                    "pyorbit_name": "SCL_Mag:DCV15"
                },
                "SCL_Mag:DCH16": {
                    "pyorbit_name": "SCL_Mag:DCH16"
                },
                "SCL_Mag:DCV16": {
                    "pyorbit_name": "SCL_Mag:DCV16"
                },
                "SCL_Mag:DCH17": {
                    "pyorbit_name": "SCL_Mag:DCH17"
                },
                "SCL_Mag:DCV17": {
                    "pyorbit_name": "SCL_Mag:DCV17"
                },
                "SCL_Mag:DCH18": {
                    "pyorbit_name": "SCL_Mag:DCH18"
                },
                "SCL_Mag:DCV18": {
                    "pyorbit_name": "SCL_Mag:DCV18"
                },
                "SCL_Mag:DCH19": {
                    "pyorbit_name": "SCL_Mag:DCH19"
                },
                "SCL_Mag:DCV19": {
                    "pyorbit_name": "SCL_Mag:DCV19"
                },
                "SCL_Mag:DCH20": {
                    "pyorbit_name": "SCL_Mag:DCH20"
                },
                "SCL_Mag:DCV20": {
                    "pyorbit_name": "SCL_Mag:DCV20"
                },
                "SCL_Mag:DCH21": {
                    "pyorbit_name": "SCL_Mag:DCH21"
                },
                "SCL_Mag:DCV21": {
                    "pyorbit_name": "SCL_Mag:DCV21"
                },
                "SCL_Mag:DCH22": {
                    "pyorbit_name": "SCL_Mag:DCH22"
                },
                "SCL_Mag:DCV22": {
                    "pyorbit_name": "SCL_Mag:DCV22"
                },
                "SCL_Mag:DCH23": {
                    "pyorbit_name": "SCL_Mag:DCH23"
                },
                "SCL_Mag:DCV23": {
                    "pyorbit_name": "SCL_Mag:DCV23"
                },
                "SCL_Mag:DCH24": {
                    "pyorbit_name": "SCL_Mag:DCH24"
                },
                "SCL_Mag:DCV24": {
                    "pyorbit_name": "SCL_Mag:DCV24"
                },
                "SCL_Mag:DCH25": {
                    "pyorbit_name": "SCL_Mag:DCH25"
                },
                "SCL_Mag:DCV25": {
                    "pyorbit_name": "SCL_Mag:DCV25"
                },
                "SCL_Mag:DCH26": {
                    "pyorbit_name": "SCL_Mag:DCH26"
                },
                "SCL_Mag:DCV26": {
                    "pyorbit_name": "SCL_Mag:DCV26"
                },
                "SCL_Mag:DCH27": {
                    "pyorbit_name": "SCL_Mag:DCH27"
                },
                "SCL_Mag:DCV27": {
                    "pyorbit_name": "SCL_Mag:DCV27"
                },
                "SCL_Mag:DCH28": {
                    "pyorbit_name": "SCL_Mag:DCH28"
                },
                "SCL_Mag:DCV28": {
                    "pyorbit_name": "SCL_Mag:DCV28"
                },
                "SCL_Mag:DCH29": {
                    "pyorbit_name": "SCL_Mag:DCH29"
                },
                "SCL_Mag:DCV29": {
                    "pyorbit_name": "SCL_Mag:DCV29"
                },
                "SCL_Mag:DCH30": {
                    "pyorbit_name": "SCL_Mag:DCH30"
                },
                "SCL_Mag:DCV30": {
                    "pyorbit_name": "SCL_Mag:DCV30"
                },
                "SCL_Mag:DCH31": {
                    "pyorbit_name": "SCL_Mag:DCH31"
                },
                "SCL_Mag:DCV31": {
                    "pyorbit_name": "SCL_Mag:DCV31"
                },
                "SCL_Mag:DCH32": {
                    "pyorbit_name": "SCL_Mag:DCH32"
                },
                "SCL_Mag:DCV32": {
                    "pyorbit_name": "SCL_Mag:DCV32"
                },
                "SCL_Mag:DCH33": {
                    "pyorbit_name": "SCL_Mag:DCH33"
                },
                "HEBT_Mag:DCV05": {
                    "pyorbit_name": "HEBT_Mag:DCV05"
                },
                "HEBT_Mag:DCH06": {
                    "pyorbit_name": "HEBT_Mag:DCH06"
                },
                "HEBT_Mag:DCV07": {
                    "pyorbit_name": "HEBT_Mag:DCV07"
                },
                "HEBT_Mag:DCH08": {
                    "pyorbit_name": "HEBT_Mag:DCH08"
                }
            }
        },
        "BPMs": {
            "parameters": {
                "xAvg": {
                    "parameter_key": "x_avg",
                    "pv_type": "diagnostic",
                    "noise": 1e-07
                },
                "yAvg": {
                    "parameter_key": "y_avg",
                    "pv_type": "diagnostic",
                    "noise": 1e-07
                },
                "phaseAvg": {
                    "parameter_key": "phi_avg",
                    "pv_type": "diagnostic",
                    "noise": 0.001
                }
            },
            "devices": {
                "SCL_Diag:BPM00a": {
                    "pyorbit_name": "SCL_Diag:BPM00a",
                    "override": {
                        "phaseAvg": {
                            "phase_offset": -172.73432241504702
                        }
                    }
                },
                "SCL_Diag:BPM00b": {
                    "pyorbit_name": "SCL_Diag:BPM00b",
                    "override": {
                        "phaseAvg": {
                            "phase_offset": -51.793298030907174
                        }
                    }
                },
                "SCL_Diag:BPM01": {
                    "pyorbit_name": "SCL_Diag:BPM01",
                    "override": {
                        "phaseAvg": {
                            "phase_offset": -33.78158150505807
                        }
                    }
                },
                "SCL_Diag:BPM02": {
                    "pyorbit_name": "SCL_Diag:BPM02",
                    "override": {
                        "phaseAvg": {
                            "phase_offset": 153.30796906014083
                        }
                    }
                },
                "SCL_Diag:BPM03": {
                    "pyorbit_name": "SCL_Diag:BPM03",
                    "override": {
                        "phaseAvg": {
                            "phase_offset": 29.8554549559967
                        }
                    }
                },
                "SCL_Diag:BPM04": {
                    "pyorbit_name": "SCL_Diag:BPM04",
                    "override": {
                        "phaseAvg": {
                            "phase_offset": -1.3022791950685209
                        }
                    }
                },
                "SCL_Diag:BPM05": {
                    "pyorbit_name": "SCL_Diag:BPM05",
                    "override": {
                        "phaseAvg": {
                            "phase_offset": 56.15052589355861
                        }
                    }
                },
                "SCL_Diag:BPM06": {
                    "pyorbit_name": "SCL_Diag:BPM06",
                    "override": {
                        "phaseAvg": {
                            "phase_offset": 72.84189295233537
                        }
                    }
                },
                "SCL_Diag:BPM07": {
                    "pyorbit_name": "SCL_Diag:BPM07",
                    "override": {
                        "phaseAvg": {
                            "phase_offset": 118.8923699722977
                        }
                    }
                },
                "SCL_Diag:BPM08": {
                    "pyorbit_name": "SCL_Diag:BPM08",
                    "override": {
                        "phaseAvg": {
                            "phase_offset": -162.71104256684723
                        }
                    }
                },
                "SCL_Diag:BPM09": {
                    "pyorbit_name": "SCL_Diag:BPM09",
                    "override": {
                        "phaseAvg": {
                            "phase_offset": 172.31942296920286
                        }
                    }
                },
                "SCL_Diag:BPM10": {
                    "pyorbit_name": "SCL_Diag:BPM10",
                    "override": {
                        "phaseAvg": {
                            "phase_offset": 44.623740138615084
                        }
                    }
                },
                "SCL_Diag:BPM11": {
                    "pyorbit_name": "SCL_Diag:BPM11",
                    "override": {
                        "phaseAvg": {
                            "phase_offset": -87.29462783020105
                        }
                    }
                },
                "SCL_Diag:BPM12": {
                    "pyorbit_name": "SCL_Diag:BPM12",
                    "override": {
                        "phaseAvg": {
                            "phase_offset": -112.55763656145076
                        }
                    }
                },
                "SCL_Diag:BPM13": {
                    "pyorbit_name": "SCL_Diag:BPM13",
                    "override": {
                        "phaseAvg": {
                            "phase_offset": -162.8349910745508
                        }
                    }
                },
                "SCL_Diag:BPM14": {
                    "pyorbit_name": "SCL_Diag:BPM14",
                    "override": {
                        "phaseAvg": {
                            "phase_offset": -160.91006246880676
                        }
                    }
                },
                "SCL_Diag:BPM15": {
                    "pyorbit_name": "SCL_Diag:BPM15",
                    "override": {
                        "phaseAvg": {
                            "phase_offset": -118.47337341786611
                        }
                    }
                },
                "SCL_Diag:BPM16": {
                    "pyorbit_name": "SCL_Diag:BPM16",
                    "override": {
                        "phaseAvg": {
                            "phase_offset": -16.532246454222662
                        }
                    }
                },
                "SCL_Diag:BPM17": {
                    "pyorbit_name": "SCL_Diag:BPM17",
                    "override": {
                        "phaseAvg": {
                            "phase_offset": 23.87500225056451
                        }
                    }
                },
                "SCL_Diag:BPM18": {
                    "pyorbit_name": "SCL_Diag:BPM18",
                    "override": {
                        "phaseAvg": {
                            "phase_offset": -20.83415669634026
                        }
                    }
                },
                "SCL_Diag:BPM19": {
                    "pyorbit_name": "SCL_Diag:BPM19",
                    "override": {
                        "phaseAvg": {
                            "phase_offset": -142.3134202311485
                        }
                    }
                },
                "SCL_Diag:BPM20": {
                    "pyorbit_name": "SCL_Diag:BPM20",
                    "override": {
                        "phaseAvg": {
                            "phase_offset": -54.705413058687604
                        }
                    }
                },
                "SCL_Diag:BPM21": {
                    "pyorbit_name": "SCL_Diag:BPM21",
                    "override": {
                        "phaseAvg": {
                            "phase_offset": -40.599709010102934
                        }
                    }
                },
                "SCL_Diag:BPM22": {
                    "pyorbit_name": "SCL_Diag:BPM22",
                    "override": {
                        "phaseAvg": {
                            "phase_offset": 19.67807366444676
                        }
                    }
                },
                "SCL_Diag:BPM23": {
                    "pyorbit_name": "SCL_Diag:BPM23",
                    "override": {
                        "phaseAvg": {
                            "phase_offset": 69.43892185336115
                        }
                    }
                },
                "SCL_Diag:BPM24": {
                    "pyorbit_name": "SCL_Diag:BPM24",
                    "override": {
                        "phaseAvg": {
                            "phase_offset": 149.40885922861833
                        }
                    }
                },
                "SCL_Diag:BPM25": {
                    "pyorbit_name": "SCL_Diag:BPM25",
                    "override": {
                        "phaseAvg": {
                            "phase_offset": 58.532586278081084
                        }
                    }
                },
                "SCL_Diag:BPM26": {
                    "pyorbit_name": "SCL_Diag:BPM26",
                    "override": {
                        "phaseAvg": {
                            "phase_offset": 31.132815669991864
                        }
                    }
                },
                "SCL_Diag:BPM27": {
                    "pyorbit_name": "SCL_Diag:BPM27",
                    "override": {
                        "phaseAvg": {
                            "phase_offset": -27.87560799083048
                        }
                    }
                },
                "SCL_Diag:BPM28": {
                    "pyorbit_name": "SCL_Diag:BPM28",
                    "override": {
                        "phaseAvg": {
                            "phase_offset": 179.65236171705658
                        }
                    }
                },
                "SCL_Diag:BPM29": {
                    "pyorbit_name": "SCL_Diag:BPM29",
                    "override": {
                        "phaseAvg": {
                            "phase_offset": -46.0946764585177
                        }
                    }
                },
                "SCL_Diag:BPM30": {
                    "pyorbit_name": "SCL_Diag:BPM30",
                    "override": {
                        "phaseAvg": {
                            "phase_offset": 66.21184824922649
                        }
                    }
                },
                "SCL_Diag:BPM31": {
                    "pyorbit_name": "SCL_Diag:BPM31",
                    "override": {
                        "phaseAvg": {
                            "phase_offset": 170.86974738539558
                        }
                    }
                },
                "SCL_Diag:BPM32": {
                    "pyorbit_name": "SCL_Diag:BPM32",
                    "override": {
                        "phaseAvg": {
                            "phase_offset": -142.90562604806698
                        }
                    }
                },
                "HEBT_Diag:BPM01": {
                    "pyorbit_name": "HEBT_Diag:BPM01",
                    "override": {
                        "phaseAvg": {
                            "phase_offset": -116.44740804635346
                        }
                    }
                },
                "HEBT_Diag:BPM02": {
                    "pyorbit_name": "HEBT_Diag:BPM02",
                    "override": {
                        "phaseAvg": {
                            "phase_offset": 70.6042679201461
                        }
                    }
                },
                "HEBT_Diag:BPM03": {
                    "pyorbit_name": "HEBT_Diag:BPM03",
                    "override": {
                        "phaseAvg": {
                            "phase_offset": -66.2131306470501
                        }
                    }
                },
                "HEBT_Diag:BPM04": {
                    "pyorbit_name": "HEBT_Diag:BPM04",
                    "override": {
                        "phaseAvg": {
                            "phase_offset": -131.99614076495803
                        }
                    }
                },
                "HEBT_Diag:BPM05": {
                    "pyorbit_name": "HEBT_Diag:BPM05",
                    "override": {
                        "phaseAvg": {
                            "phase_offset": 27.390691760687595
                        }
                    }
                },
                "HEBT_Diag:BPM06": {
                    "pyorbit_name": "HEBT_Diag:BPM06",
                    "override": {
                        "phaseAvg": {
                            "phase_offset": -66.39821451819303
                        }
                    }
                },
                "HEBT_Diag:BPM07": {
                    "pyorbit_name": "HEBT_Diag:BPM07",
                    "override": {
                        "phaseAvg": {
                            "phase_offset": 165.77905259978098
                        }
                    }
                },
                "HEBT_Diag:BPM08": {
                    "pyorbit_name": "HEBT_Diag:BPM08",
                    "override": {
                        "phaseAvg": {
                            "phase_offset": 173.82080276688265
                        }
                    }
                },
                "HEBT_Diag:BPM09": {
                    "pyorbit_name": "HEBT_Diag:BPM09",
                    "override": {
                        "phaseAvg": {
                            "phase_offset": 24.06758279111296
                        }
                    }
                },
                "HEBT_Diag:BPM10": {
                    "pyorbit_name": "HEBT_Diag:BPM10",
                    "override": {
                        "phaseAvg": {
                            "phase_offset": -56.902312013394955
                        }
                    }
                },
                "HEBT_Diag:BPM11": {
                    "pyorbit_name": "HEBT_Diag:BPM11",
                    "override": {
                        "phaseAvg": {
                            "phase_offset": -51.095889195883366
                        }
                    }
                }
            }
        },
        "PBPMs": {
            "parameters": {
                "Energy": {
                    "parameter_key": "energy",
                    "pv_type": "physics"
                },
                "Beta": {
                    "parameter_key": "beta",
                    "pv_type": "physics"
                }
            },
            "devices": {
                "SCL_Phys:BPM00a": {
                    "pyorbit_name": "SCL_Diag:BPM00a"
                },
                "SCL_Phys:BPM00b": {
                    "pyorbit_name": "SCL_Diag:BPM00b"
                },
                "SCL_Phys:BPM01": {
                    "pyorbit_name": "SCL_Diag:BPM01"
                },
                "SCL_Phys:BPM02": {
                    "pyorbit_name": "SCL_Diag:BPM02"
                },
                "SCL_Phys:BPM03": {
                    "pyorbit_name": "SCL_Diag:BPM03"
                },
                "SCL_Phys:BPM04": {
                    "pyorbit_name": "SCL_Diag:BPM04"
                },
                "SCL_Phys:BPM05": {
                    "pyorbit_name": "SCL_Diag:BPM05"
                },
                "SCL_Phys:BPM06": {
                    "pyorbit_name": "SCL_Diag:BPM06"
                },
                "SCL_Phys:BPM07": {
                    "pyorbit_name": "SCL_Diag:BPM07"
                },
                "SCL_Phys:BPM08": {
                    "pyorbit_name": "SCL_Diag:BPM08"
                },
                "SCL_Phys:BPM09": {
                    "pyorbit_name": "SCL_Diag:BPM09"
                },
                "SCL_Phys:BPM10": {
                    "pyorbit_name": "SCL_Diag:BPM10"
                },
                "SCL_Phys:BPM11": {
                    "pyorbit_name": "SCL_Diag:BPM11"
                },
                "SCL_Phys:BPM12": {
                    "pyorbit_name": "SCL_Diag:BPM12"
                },
                "SCL_Phys:BPM13": {
                    "pyorbit_name": "SCL_Diag:BPM13"
                },
                "SCL_Phys:BPM14": {
                    "pyorbit_name": "SCL_Diag:BPM14"
                },
                "SCL_Phys:BPM15": {
                    "pyorbit_name": "SCL_Diag:BPM15"
                },
                "SCL_Phys:BPM16": {
                    "pyorbit_name": "SCL_Diag:BPM16"
                },
                "SCL_Phys:BPM17": {
                    "pyorbit_name": "SCL_Diag:BPM17"
                },
                "SCL_Phys:BPM18": {
                    "pyorbit_name": "SCL_Diag:BPM18"
                },
                "SCL_Phys:BPM19": {
                    "pyorbit_name": "SCL_Diag:BPM19"
                },
                "SCL_Phys:BPM20": {
                    "pyorbit_name": "SCL_Diag:BPM20"
                },
                "SCL_Phys:BPM21": {
                    "pyorbit_name": "SCL_Diag:BPM21"
                },
                "SCL_Phys:BPM22": {
                    "pyorbit_name": "SCL_Diag:BPM22"
                },
                "SCL_Phys:BPM23": {
                    "pyorbit_name": "SCL_Diag:BPM23"
                },
                "SCL_Phys:BPM24": {
                    "pyorbit_name": "SCL_Diag:BPM24"
                },
                "SCL_Phys:BPM25": {
                    "pyorbit_name": "SCL_Diag:BPM25"
                },
                "SCL_Phys:BPM26": {
                    "pyorbit_name": "SCL_Diag:BPM26"
                },
                "SCL_Phys:BPM27": {
                    "pyorbit_name": "SCL_Diag:BPM27"
                },
                "SCL_Phys:BPM28": {
                    "pyorbit_name": "SCL_Diag:BPM28"
                },
                "SCL_Phys:BPM29": {
                    "pyorbit_name": "SCL_Diag:BPM29"
                },
                "SCL_Phys:BPM30": {
                    "pyorbit_name": "SCL_Diag:BPM30"
                },
                "SCL_Phys:BPM31": {
                    "pyorbit_name": "SCL_Diag:BPM31"
                },
                "SCL_Phys:BPM32": {
                    "pyorbit_name": "SCL_Diag:BPM32"
                },
                "HEBT_Phys:BPM01": {
                    "pyorbit_name": "HEBT_Diag:BPM01"
                },
                "HEBT_Phys:BPM02": {
                    "pyorbit_name": "HEBT_Diag:BPM02"
                },
                "HEBT_Phys:BPM03": {
                    "pyorbit_name": "HEBT_Diag:BPM03"
                },
                "HEBT_Phys:BPM04": {
                    "pyorbit_name": "HEBT_Diag:BPM04"
                },
                "HEBT_Phys:BPM05": {
                    "pyorbit_name": "HEBT_Diag:BPM05"
                },
                "HEBT_Phys:BPM06": {
                    "pyorbit_name": "HEBT_Diag:BPM06"
                },
                "HEBT_Phys:BPM07": {
                    "pyorbit_name": "HEBT_Diag:BPM07"
                },
                "HEBT_Phys:BPM08": {
                    "pyorbit_name": "HEBT_Diag:BPM08"
                },
                "HEBT_Phys:BPM09": {
                    "pyorbit_name": "HEBT_Diag:BPM09"
                },
                "HEBT_Phys:BPM10": {
                    "pyorbit_name": "HEBT_Diag:BPM10"
                },
                "HEBT_Phys:BPM11": {
                    "pyorbit_name": "HEBT_Diag:BPM11"
                }
            }
        }
    }
}